verilog_codes/exp3/and_or.v

module addor(a,b,c,y);
    input a,b,c;
    output y;
    wire and_op1, and_op2, and_op3, and_op4, and_op5;
    and g1(and_op1,~a,~c);
    and g2(and_op2,~a,c);
    and g3(and_op3,a,~b);

    or g4(and_op4, and_op1, and_op2);
    or g5(and_op5, and_op3, and_op4);
    or g6(y, and_op5, and_op4);

endmodule

module testbench;
        reg a,b,c,d;
        wire y;
        addor ao(a,b,c,y);
        initial begin
                    $dumpfile("and_or.vcd");
                    $dumpvars(0,testbench);
                    a=0;b=0;c=0;
                     #5
                    a=0;b=0;c=1;
                     #5
                    a=0;b=1;c=0;
                     #5
                    a=0;b=1;c=1;
                     #5
                    a=1;b=0;c=0;
                     #5
                    a=1;b=0;c=1;
                     #5
                    a=1;b=1;c=0;
                     #5
                    a=1;b=1;c=1;  
                     $finish;  
        end

endmodule

verilog_codes/exp3/and_or.vcd
$date
	Wed Jan 26 23:50:59 2022
$end
$version
	Icarus Verilog
$end
$timescale
	1s
$end
$scope module testbench $end
$var wire 1 ! y $end
$var reg 1 " a $end
$var reg 1 # b $end
$var reg 1 $ c $end
$scope module ao $end
$var wire 1 " a $end
$var wire 1 % and_op1 $end
$var wire 1 & and_op2 $end
$var wire 1 ' and_op3 $end
$var wire 1 ( and_op4 $end
$var wire 1 ) and_op5 $end
$var wire 1 # b $end
$var wire 1 $ c $end
$var wire 1 ! y $end
$upscope $end
$upscope $end
$enddefinitions $end
#0
$dumpvars
1)
1(
0'
0&
1%
0$
0#
0"
1!
$end
#5
0%
1&
1$
#10
1)
1%
1(
0&
0$
1#
#15
0%
1&
1$
#20
0(
1'
0&
0$
0#
1"
#25
1$
#30
0!
0)
0'
0$
1#
#35
1$
