verilog_codes/exp8/JKff.v
module JK_FF(jk, clk, q, qb);
    input[1:0]jk;
    input clk;
    output reg q=1'b0;
    output reg qb;
    always@(posedge clk)
    begin
            case(jk)
                    2'b00:q=q;
                    2'b01:q=1'b0; 
                    2'b10:q=1'b1; 
                    2'b11:q=~q; 
            endcase
            qb=~q;
    end
endmodule

module testbench;
    reg[1:0]A;
    reg c;
    wire x, xb;
    JK_FF jkff(A, c,x, xb);
    initial c=1'b0;
    always #5 c=~c;
    initial begin
            $dumpfile("JKff.vcd");
            $dumpvars(0,testbench);
            A=2'b00;#10;
            A=2'b01;#10;
            A=2'b10;#10;
            A=2'b11;
            #20
            $finish;
    end
endmodule

verilog_codes/exp8/JKff.vcd
$date
	Thu Jan 27 09:00:35 2022
$end
$version
	Icarus Verilog
$end
$timescale
	1s
$end
$scope module testbench $end
$var wire 1 ! xb $end
$var wire 1 " x $end
$var reg 2 # A [1:0] $end
$var reg 1 $ c $end
$scope module jkff $end
$var wire 1 $ clk $end
$var wire 2 % jk [1:0] $end
$var reg 1 " q $end
$var reg 1 ! qb $end
$upscope $end
$upscope $end
$enddefinitions $end
#0
$dumpvars
b0 %
0$
b0 #
0"
x!
$end
#5
1!
1$
#10
0$
b1 #
b1 %
#15
1$
#20
0$
b10 #
b10 %
#25
0!
1"
1$
#30
0$
b11 #
b11 %
#35
1!
0"
1$
#40
0$
#45
0!
1"
1$
